README.md
setup.py
aiorosapi/__init__.py
aiorosapi/exceptions.py
aiorosapi/packet.py
aiorosapi/protocol.py
aiorosapi/utils.py
aiorosapi.egg-info/PKG-INFO
aiorosapi.egg-info/SOURCES.txt
aiorosapi.egg-info/dependency_links.txt
aiorosapi.egg-info/top_level.txt