Metadata-Version: 2.1
Name: aiorosapi
Version: 0.2.5
Summary: UNKNOWN
Home-page: https://github.com/gaussgss/aiorosapi
Author: Andrey Gusev
Author-email: gaussgss@gmail.com
License: UNKNOWN
Platform: UNKNOWN
Classifier: Programming Language :: Python :: 3
Classifier: License :: OSI Approved :: MIT License
Classifier: Operating System :: OS Independent
